{
  "project_info": {
    "project_number": "112670824090",
    "firebase_url": "https://lumeai-banking-demo-default-rtdb.firebaseio.com",
    "project_id": "lumeai-banking-demo",
    "storage_bucket": "lumeai-banking-demo.firebasestorage.app"
  },
  "client": [
    {
      "client_info": {
        "mobilesdk_app_id": "1:112670824090:android:167f81f6ffd972b8fef123",
        "android_client_info": {
          "package_name": "com.lumeai.banking"
        }
      },
      "oauth_client": [],
      "api_key": [
        {
          "current_key": "AIzaSyD_o-fvzBSnJjFCnyNvJfC1WB8rdAAQ14o"
        }
      ],
      "services": {
        "appinvite_service": {
          "other_platform_oauth_client": []
        }
      }
    }
  ],
  "configuration_version": "1"
}